logover/__init__.py
logover-0.0.1.dist-info/LICENSE.txt
logover-0.0.1.dist-info/METADATA
logover-0.0.1.dist-info/WHEEL
logover-0.0.1.dist-info/top_level.txt
logover-0.0.1.dist-info/RECORD
